cs/configutils.py
cs_configutils-20250103.dist-info/METADATA
cs_configutils-20250103.dist-info/WHEEL
cs_configutils-20250103.dist-info/top_level.txt
cs_configutils-20250103.dist-info/RECORD
